CHANGELOG.rst
MANIFEST.in
README.rst
setup.py
echarts_china_misc_pypkg/__init__.py
echarts_china_misc_pypkg/_version.py
echarts_china_misc_pypkg.egg-info/PKG-INFO
echarts_china_misc_pypkg.egg-info/SOURCES.txt
echarts_china_misc_pypkg.egg-info/dependency_links.txt
echarts_china_misc_pypkg.egg-info/not-zip-safe
echarts_china_misc_pypkg.egg-info/requires.txt
echarts_china_misc_pypkg.egg-info/top_level.txt
echarts_china_misc_pypkg/resources/registry.json
echarts_china_misc_pypkg/resources/echarts-china-misc-js/china-regions.js
echarts_china_misc_pypkg/resources/echarts-china-misc-js/dong1_bei3.js
echarts_china_misc_pypkg/resources/echarts-china-misc-js/hua2_bei3.js
echarts_china_misc_pypkg/resources/echarts-china-misc-js/hua2_dong1.js
echarts_china_misc_pypkg/resources/echarts-china-misc-js/hua2_nan2.js
echarts_china_misc_pypkg/resources/echarts-china-misc-js/hua2_nan2_2.js
echarts_china_misc_pypkg/resources/echarts-china-misc-js/hua2_zhong1.js
echarts_china_misc_pypkg/resources/echarts-china-misc-js/index.js
echarts_china_misc_pypkg/resources/echarts-china-misc-js/su_wan_zhe.js
echarts_china_misc_pypkg/resources/echarts-china-misc-js/tai2_gang3_ao4.js
echarts_china_misc_pypkg/resources/echarts-china-misc-js/xi1_bei3.js
echarts_china_misc_pypkg/resources/echarts-china-misc-js/xi1_nan2.js